{
  "gitSyncId": "68edbca07f897134d9d213fe_d7bafe95-777e-4964-ae2e-99c7748f64a3",
  "id": "ChallengeDetail_PageLogic.updateEndTime",
  "pluginId": "js-plugin",
  "pluginType": "JS",
  "unpublishedAction": {
    "actionConfiguration": {
      "encodeParamsToggle": true,
      "jsArguments": [],
      "paginationType": "NONE",
      "timeoutInMillisecond": 10000
    },
    "collectionId": "ChallengeDetail_PageLogic",
    "confirmBeforeExecute": false,
    "datasource": {
      "isAutoGenerated": false,
      "name": "UNUSED_DATASOURCE",
      "pluginId": "js-plugin"
    },
    "dynamicBindingPathList": [
      {
        "key": "body"
      }
    ],
    "fullyQualifiedName": "PageLogic.updateEndTime",
    "name": "updateEndTime",
    "pageId": "ChallengeDetail",
    "runBehaviour": "MANUAL",
    "userSetOnLoad": false
  }
}