{
  "gitSyncId": "68edbca07f897134d9d213fe_5fcb84f5-3837-4922-b126-1202e72c3134",
  "id": "RewardList_getAppToken.getUserEmail",
  "pluginId": "js-plugin",
  "pluginType": "JS",
  "unpublishedAction": {
    "actionConfiguration": {
      "encodeParamsToggle": true,
      "jsArguments": [],
      "paginationType": "NONE",
      "timeoutInMillisecond": 10000
    },
    "collectionId": "RewardList_getAppToken",
    "confirmBeforeExecute": false,
    "datasource": {
      "isAutoGenerated": false,
      "name": "UNUSED_DATASOURCE",
      "pluginId": "js-plugin"
    },
    "dynamicBindingPathList": [
      {
        "key": "body"
      }
    ],
    "fullyQualifiedName": "getAppToken.getUserEmail",
    "name": "getUserEmail",
    "pageId": "RewardList",
    "runBehaviour": "MANUAL",
    "userSetOnLoad": false
  }
}